{"Sardinian": {"language_names": {"regular": {"Afrikaans": {"wiki_name": {"name": "Limba afrikaans"}, "clf_name": "afrik-defau-latn-defau"}, "Albanian": {"wiki_name": {"name": "Limba albanesa"}, "clf_name": "alban-defau-latn-defau"}, "Amharic": {"wiki_name": {"name": "Limba amarica"}, "clf_name": "amhar-defau-ethi-defau"}, "Aragonese": {"lingvoj_names": [{"name": "Limba aragonesa"}], "wiki_name": {"name": "Limba araba"}, "clf_name": "arago-defau-latn-defau"}, "Asturian": {"wiki_name": {"name": "Limba asturiana"}, "clf_name": "astur-defau-latn-defau"}, "Basque": {"lingvoj_names": [{"name": "Limba basca"}], "wiki_name": {"name": "Limba basca"}, "clf_name": "basqu-defau-latn-defau"}, "Catalan": {"lingvoj_names": [{"name": "Limba catalana"}], "wiki_name": {"name": "Limba catalana"}, "clf_name": "catal-defau-latn-defau"}, "Corsican": {"lingvoj_names": [{"name": "Tàtaresu"}, {"name": "Galluresu"}], "wiki_name": {"name": "Limba corsicana"}, "clf_name": "corsi-defau-latn-defau"}, "Croatian": {"lingvoj_names": [{"name": "Limba croata"}], "wiki_name": {"name": "Limba croata"}, "clf_name": "shtok-croat-latn-defau"}, "Danish": {"wiki_name": {"name": "Limba danesa"}, "clf_name": "danis-defau-latn-defau"}, "Dutch": {"wiki_name": {"name": "Limba olandesa"}, "clf_name": "dutch-defau-latn-defau"}, "Emiliano-Romagnolo": {"wiki_name": {"name": "Emilianu-Romagnolu"}, "clf_name": "emiro-defau-latn-defau"}, "English": {"wiki_name": {"name": "Limba inglesa"}, "clf_name": "engli-defau-latn-defau"}, "Esperanto": {"lingvoj_names": [{"name": "Esperanto"}], "wiki_name": {"name": "Esperanto"}, "clf_name": "esper-defau-latn-defau"}, "Estonian": {"wiki_name": {"name": "Limba ispagnola"}, "clf_name": "eston-defau-latn-defau"}, "Faroese": {"wiki_name": {"name": "Limba faroesa"}, "clf_name": "faroe-defau-latn-defau"}, "French": {"lingvoj_names": [{"name": "Limba frantzesa"}], "wiki_name": {"name": "Limba frantzesa"}, "clf_name": "franc-defau-latn-defau"}, "Friulian": {"wiki_name": {"name": "Limba friulana"}, "clf_name": "friul-defau-latn-defau"}, "Galician": {"wiki_name": {"name": "Limba galega"}, "clf_name": "galic-defau-latn-defau"}, "German": {"wiki_name": {"name": "Limba tedesca"}, "clf_name": "germa-defau-latn-defau"}, "Greek": {"wiki_name": {"name": "Limba grega"}, "clf_name": "greek-defau-grek-defau"}, "Hebrew": {"wiki_name": {"name": "Limba ebrea"}, "clf_name": "hebre-defau-hebr-defau"}, "Hungarian": {"wiki_name": {"name": "Limba ungheresa"}, "clf_name": "hunga-defau-latn-defau"}, "Icelandic": {"wiki_name": {"name": "Limba islandesa"}, "clf_name": "icela-defau-latn-defau"}, "Ido": {"wiki_name": {"name": "Ido"}, "clf_name": "idola-defau-latn-defau"}, "Interlingua": {"wiki_name": {"name": "Interlingua"}, "clf_name": "intea-defau-latn-defau"}, "Irish": {"lingvoj_names": [{"name": "Gaelicu Irlandiesu"}], "wiki_name": {"name": "Gaelicu Irlandiesu"}, "clf_name": "irish-defau-latn-defau"}, "Italian": {"lingvoj_names": [{"name": "Limba italiana"}], "wiki_name": {"name": "Limba italiana"}, "clf_name": "itali-defau-latn-defau"}, "Japanese": {"wiki_name": {"name": "Limba giapponesa"}, "clf_name": "japan-defau-japn-defau"}, "Judaeo-Spanish": {"lingvoj_names": [{"name": "Limba ladina"}], "wiki_name": {"name": "Limba ladina"}, "clf_name": "judsp-defau-latn-defau"}, "Korean": {"wiki_name": {"name": "Limba coreana"}, "clf_name": "korea-defau-kore-defau"}, "Latin": {"lingvoj_names": [{"name": "Limba latina"}], "wiki_name": {"name": "Limba latina"}, "clf_name": "latin-defau-latn-defau"}, "Lombard": {"wiki_name": {"name": "Limba lombarda"}, "clf_name": "lomba-defau-latn-defau"}, "Low Saxon": {"wiki_name": {"name": "Bassu tedescu"}, "clf_name": "saxlo-germa-latn-defau"}, "Maltese": {"wiki_name": {"name": "Limba maltesa"}, "clf_name": "malte-defau-latn-defau"}, "Maori": {"wiki_name": {"name": "Limba māori"}, "clf_name": "maori-defau-latn-defau"}, "Neapolitan": {"wiki_name": {"name": "Limba napulitana"}, "clf_name": "neapo-defau-latn-defau"}, "Occitan": {"lingvoj_names": [{"name": "Limba otzitana"}], "wiki_name": {"name": "Limba otzitana"}, "clf_name": "occit-defau-latn-defau"}, "Polish": {"wiki_name": {"name": "Limba polonesa"}, "clf_name": "polis-defau-latn-defau"}, "Portuguese": {"wiki_name": {"name": "Limba portughesa"}, "clf_name": "portu-defau-latn-defau"}, "Romanian": {"lingvoj_names": [{"name": "Limba romuna"}], "wiki_name": {"name": "Limba romuna"}, "clf_name": "roman-defau-latn-defau"}, "Romansh": {"wiki_name": {"name": "Limba romancia"}, "clf_name": "rmnsh-defau-latn-defau"}, "Russian": {"wiki_name": {"name": "Limba russa"}, "clf_name": "russi-defau-cyrl-defau"}, "Rusyn": {"wiki_name": {"name": "Limba rutena"}, "clf_name": "rusyn-defau-cyrl-defau"}, "Sardinian": {"lingvoj_names": [{"name": "Limba sarda"}], "wiki_name": {"name": "Limba sarda"}, "clf_name": "sardi-defau-latn-defau"}, "Scots": {"wiki_name": {"name": "Scots"}, "clf_name": "scots-defau-latn-defau"}, "Scots Gaelic": {"lingvoj_names": [{"name": "Limba gaelica scotzesa"}], "wiki_name": {"name": "Limba gaelica scotzesa"}, "clf_name": "scoga-defau-latn-defau"}, "Serbo-Croatian": {"lingvoj_names": [{"name": "Limba serbocroata"}], "wiki_name": {"name": "Limba serbocroata"}, "clf_name": "shtok-sercr-lacy-defau"}, "Sicilian": {"lingvoj_names": [{"name": "Limba sitziliana"}], "wiki_name": {"name": "Limba sitziliana"}, "clf_name": "sicil-defau-latn-defau"}, "Simple English": {"lingvoj_names": [{"name": "Limba inglesa"}], "clf_name": "engli-simpl-latn-defau"}, "Slovak": {"wiki_name": {"name": "Limba Islovaca"}, "clf_name": "slova-defau-latn-defau"}, "Slovene": {"wiki_name": {"name": "Limba islovena"}, "clf_name": "slove-defau-latn-defau"}, "Spanish": {"lingvoj_names": [{"name": "Limba ispagnola"}], "clf_name": "spani-defau-latn-defau"}, "Swedish": {"wiki_name": {"name": "Limba isvedesa"}, "clf_name": "swedi-defau-latn-defau"}, "Turkish": {"lingvoj_names": [{"name": "Lìngua turca"}], "wiki_name": {"name": "Lìngua turca"}, "clf_name": "turki-defau-latn-defau"}, "Ukrainian": {"wiki_name": {"name": "Limba ucraina"}, "clf_name": "ukrai-defau-cyrl-defau"}, "Upper Sorbian": {"lingvoj_names": [{"name": "Limba sòraba de susu"}], "wiki_name": {"name": "Limba sòraba de susu"}, "clf_name": "sorbu-defau-latn-defau"}, "Venetian": {"wiki_name": {"name": "Limba veneta"}, "clf_name": "venet-defau-latn-defau"}, "Welsh": {"lingvoj_names": [{"name": "Limba gallesa"}], "wiki_name": {"name": "Limba gallesa"}, "clf_name": "welsh-defau-latn-defau"}, "Wu": {"lingvoj_names": [{"name": "Lingua wu"}], "wiki_name": {"name": "Lingua wu"}, "clf_name": "chine-wulan-hast-defau"}}}, "iso_639_1": "sc", "other": {"cmn": {"lingvoj_names": {"name": "Lingua xinesa mandarinu"}}, "rap": {"lingvoj_names": {"name": "Lingua Rapa Nui/campidanesu"}}, "src": {"lingvoj_names": {"name": "Sardu logudoresu"}}, "sro": {"lingvoj_names": {"name": "Sardu campidanesu"}}}, "iso_639_3": "srd", "clf_full_code": "sardi-defau-latn-defau", "wiki_code": "sc"}}